network_spatial_coherence/__init__.py
network_spatial_coherence/algorithms.py
network_spatial_coherence/check_latex_installation.py
network_spatial_coherence/config.py
network_spatial_coherence/correct_edgelist_and_colorcode.py
network_spatial_coherence/create_proximity_graph.py
network_spatial_coherence/curve_fitting.py
network_spatial_coherence/data_analysis.py
network_spatial_coherence/dimension_prediction.py
network_spatial_coherence/dna_cool2.png
network_spatial_coherence/docs_util.py
network_spatial_coherence/edge_list_us_counties.csv
network_spatial_coherence/edge_list_weighted.csv
network_spatial_coherence/example_edge_list.pickle
network_spatial_coherence/gram_matrix_analysis.py
network_spatial_coherence/make_spatial_coherence_comparative_plots.py
network_spatial_coherence/make_spatial_coherence_comparative_plots_swissroll.py
network_spatial_coherence/map_image_to_colors.py
network_spatial_coherence/metrics.py
network_spatial_coherence/nsc_pipeline.py
network_spatial_coherence/plots.py
network_spatial_coherence/process_output_dataframe_folders_clean.py
network_spatial_coherence/spatial_constant_analysis.py
network_spatial_coherence/structure_and_args.py
network_spatial_coherence/utils.py
network_spatial_coherence/docs/build/html/folder_structure.html
network_spatial_coherence/docs/build/html/genindex.html
network_spatial_coherence/docs/build/html/index.html
network_spatial_coherence/docs/build/html/main.html
network_spatial_coherence/docs/build/html/objects.inv
network_spatial_coherence/docs/build/html/py-modindex.html
network_spatial_coherence/docs/build/html/search.html
network_spatial_coherence/docs/build/html/searchindex.js
network_spatial_coherence/docs/build/html/structure_and_args.html
network_spatial_coherence/docs/build/html/tutorial.html
network_spatial_coherence/docs/build/html/_images/dimension_prediction_by_node_count_LINEAR_N=10000_dim=2_delaunay_corrected_k=15.svg
network_spatial_coherence-0.2.22.dist-info/METADATA
network_spatial_coherence-0.2.22.dist-info/WHEEL
network_spatial_coherence-0.2.22.dist-info/top_level.txt
network_spatial_coherence-0.2.22.dist-info/RECORD
