Metadata-Version: 2.1
Name: network-spatial-coherence
Version: 0.2.22
Summary: Network Validation using the Spatial Coherence Framework.
Home-page: https://github.com/DavidFernandezBonet/Spatial Constant Analysis
Author: David Fernandez Bonet
Author-email: dfb@kth.se
Classifier: Development Status :: 3 - Alpha
Classifier: Intended Audience :: Developers
Classifier: Natural Language :: English
Classifier: Operating System :: OS Independent
Classifier: Programming Language :: Python
Classifier: Programming Language :: Python :: 3
Classifier: Programming Language :: Python :: 3.8
Classifier: Programming Language :: Python :: 3.9
Classifier: Programming Language :: Python :: 3.10
Classifier: License :: OSI Approved :: MIT License
Classifier: Topic :: Software Development :: Libraries :: Python Modules
Requires-Python: >=3.8,<=3.12
Requires-Dist: matplotlib
Requires-Dist: memory-profiler (==0.61.0)
Requires-Dist: networkx
Requires-Dist: nodevectors
Requires-Dist: numpy
Requires-Dist: pandas
Requires-Dist: pecanpy
Requires-Dist: Pillow (==10.2.0)
Requires-Dist: igraph
Requires-Dist: scienceplots (==2.1.1)
Requires-Dist: scikit-learn
Requires-Dist: scipy
Requires-Dist: seaborn
Requires-Dist: umap-learn
Requires-Dist: statsmodels
Provides-Extra: dev
Requires-Dist: pytest (>=3.7) ; extra == 'dev'
Requires-Dist: check-manifest ; extra == 'dev'
Requires-Dist: twine ; extra == 'dev'
